stan2tfp/__init__.py
stan2tfp/stan2tfp.py
stan2tfp-0.1.1.dist-info/LICENSE
stan2tfp-0.1.1.dist-info/METADATA
stan2tfp-0.1.1.dist-info/WHEEL
stan2tfp-0.1.1.dist-info/top_level.txt
stan2tfp-0.1.1.dist-info/RECORD
