Metadata-Version: 2.1
Name: stan2tfp
Version: 0.1.1
Summary: a lightweight interface to the TensorFlow Probability backend of the Stan compiler.
Home-page: https://github.com/adamhaber/stan2tfp
Author: Adam Haber
Author-email: adamhaber@gmail.com
License: BSD 3-clause "New" or "Revised License"
Keywords: stan,tfp,bayesian models
Platform: UNKNOWN
Classifier: Development Status :: 2 - Pre-Alpha
Classifier: Intended Audience :: Developers
Classifier: Intended Audience :: Science/Research
Classifier: License :: OSI Approved :: BSD License
Classifier: Natural Language :: English
Classifier: Programming Language :: Python :: 3.6
Classifier: Programming Language :: Python :: 3.7
Classifier: Programming Language :: Python :: 3.9
Requires-Python: >=3.6
Requires-Dist: pip
Requires-Dist: numpy
Requires-Dist: tf-nightly
Requires-Dist: tfp-nightly
Provides-Extra: test
Requires-Dist: pytest ; extra == 'test'
